{
  "date": "2026-07-07",
  "last_updated": "2026-07-07",
  "categories": {
    "ai": {
      "name": "人工智能",
      "icon": "🤖",
      "count": 5,
      "items": [
        {
          "title": "征程赶超｜WAIC 2026理论突破：以数理双向赋能为钥，开启AI范式革新新征程",
          "link": "https://www.jiqizhixin.com/search/articles/征程赶超｜WAIC 2026理",
          "summary": "征程赶超｜WAIC 2026理论突破：以数理双向赋能为钥，开启AI范式革新新征程...",
          "date": "2026-07-06",
          "source": "机器之心",
          "type": "industry",
          "tags": [
            "AI",
            "人工智能"
          ]
        },
        {
          "title": "征程赶超｜WAIC 2026 Token经济：按下加速键，从技术计量到产业新范式",
          "link": "https://www.jiqizhixin.com/search/articles/征程赶超｜WAIC 2026 ",
          "summary": "征程赶超｜WAIC 2026 Token经济：按下加速键，从技术计量到产业新范式...",
          "date": "2026-07-06",
          "source": "机器之心",
          "type": "industry",
          "tags": [
            "AI",
            "人工智能"
          ]
        },
        {
          "title": "征程赶超｜WAIC 2026科学智能：AI4S从“辅助计算”到“自主发现”，中国如何重塑全球科研版图？",
          "link": "https://www.jiqizhixin.com/search/articles/征程赶超｜WAIC 2026科",
          "summary": "征程赶超｜WAIC 2026科学智能：AI4S从“辅助计算”到“自主发现”，中国如何重塑全球科研版图？...",
          "date": "2026-07-06",
          "source": "机器之心",
          "type": "industry",
          "tags": [
            "AI",
            "人工智能"
          ]
        },
        {
          "title": "WWW时间检验奖颁给唐建博士：图神经网络的十年远征与AI制药的底层逻辑",
          "link": "https://www.jiqizhixin.com/search/articles/WWW时间检验奖颁给唐建博士：",
          "summary": "WWW时间检验奖颁给唐建博士：图神经网络的十年远征与AI制药的底层逻辑...",
          "date": "2026-07-06",
          "source": "机器之心",
          "type": "industry",
          "tags": [
            "AI",
            "人工智能"
          ]
        },
        {
          "title": "70年前，香农就拥有了端侧私人定制大语言模型",
          "link": "https://www.qbitai.com/?s=70年前，香农就拥有",
          "summary": "70年前，香农就拥有了端侧私人定制大语言模型...",
          "date": "2026-07-07",
          "source": "量子位",
          "type": "industry",
          "tags": [
            "AI",
            "人工智能"
          ]
        }
      ]
    },
    "economy": {
      "name": "宏观经济",
      "icon": "📈",
      "count": 0,
      "items": []
    },
    "realestate": {
      "name": "房地产",
      "icon": "🏠",
      "count": 0,
      "items": []
    },
    "chip": {
      "name": "芯片半导体",
      "icon": "💻",
      "count": 0,
      "items": []
    }
  },
  "hot_topics": [
    "AI大模型",
    "美联储利率决议",
    "房贷利率",
    "芯片出口管制"
  ]
}