{
  "date": "2026-04-16",
  "last_updated": "2026-04-16",
  "categories": {
    "ai": {
      "name": "人工智能",
      "icon": "🤖",
      "count": 5,
      "items": [
        {
          "title": "推动具身智能从实验室研发迈向规模化商业落地，打造“具身智能超级供应链”。",
          "link": "https://www.qbitai.com/?s=推动具身智能从实验室",
          "summary": "推动具身智能从实验室研发迈向规模化商业落地，打造“具身智能超级供应链”。...",
          "date": "2026-04-16",
          "source": "量子位",
          "type": "industry",
          "tags": [
            "AI",
            "人工智能"
          ]
        },
        {
          "title": "创下中国具身智能有史以来最高单轮融资纪录，仅用一年时间成功领跑具身智能行业第一梯队。",
          "link": "https://www.qbitai.com/?s=创下中国具身智能有史",
          "summary": "创下中国具身智能有史以来最高单轮融资纪录，仅用一年时间成功领跑具身智能行业第一梯队。...",
          "date": "2026-04-16",
          "source": "量子位",
          "type": "industry",
          "tags": [
            "AI",
            "人工智能"
          ]
        },
        {
          "title": "手捏多位科技公司CEO及投资者“死亡名单”",
          "link": "https://www.qbitai.com/?s=手捏多位科技公司CE",
          "summary": "手捏多位科技公司CEO及投资者“死亡名单”...",
          "date": "2026-04-16",
          "source": "量子位",
          "type": "industry",
          "tags": [
            "AI",
            "人工智能"
          ]
        },
        {
          "title": "一次性获取百度智能云的全栈技术图谱",
          "link": "https://www.qbitai.com/?s=一次性获取百度智能云",
          "summary": "一次性获取百度智能云的全栈技术图谱...",
          "date": "2026-04-16",
          "source": "量子位",
          "type": "industry",
          "tags": [
            "AI",
            "人工智能"
          ]
        },
        {
          "title": "立足全球AI创新核心趋势，筑牢国芯AI发展根基",
          "link": "https://www.qbitai.com/?s=立足全球AI创新核心",
          "summary": "立足全球AI创新核心趋势，筑牢国芯AI发展根基...",
          "date": "2026-04-16",
          "source": "量子位",
          "type": "industry",
          "tags": [
            "AI",
            "人工智能"
          ]
        }
      ]
    },
    "economy": {
      "name": "宏观经济",
      "icon": "📈",
      "count": 0,
      "items": []
    },
    "realestate": {
      "name": "房地产",
      "icon": "🏠",
      "count": 0,
      "items": []
    },
    "chip": {
      "name": "芯片半导体",
      "icon": "💻",
      "count": 0,
      "items": []
    }
  },
  "hot_topics": [
    "AI大模型",
    "美联储利率决议",
    "房贷利率",
    "芯片出口管制"
  ]
}