{
  "date": "2026-07-01",
  "last_updated": "2026-07-01",
  "categories": {
    "ai": {
      "name": "人工智能",
      "icon": "🤖",
      "count": 5,
      "items": [
        {
          "title": "普朗克被撤稿了？量子之父竟被算法绊了一跤",
          "link": "https://www.jiqizhixin.com/search/articles/普朗克被撤稿了？量子之父竟被算",
          "summary": "普朗克被撤稿了？量子之父竟被算法绊了一跤...",
          "date": "2026-06-30",
          "source": "机器之心",
          "type": "industry",
          "tags": [
            "AI",
            "人工智能"
          ]
        },
        {
          "title": "OpenSquilla 上线后数周内 GitHub star 增至数千量级",
          "link": "https://www.qbitai.com/?s=OpenSquill",
          "summary": "OpenSquilla 上线后数周内 GitHub star 增至数千量级...",
          "date": "2026-07-01",
          "source": "量子位",
          "type": "industry",
          "tags": [
            "AI",
            "人工智能"
          ]
        },
        {
          "title": "Gemni 3.5 Pro到底啥时候来啊！！！",
          "link": "https://www.qbitai.com/?s=Gemni 3.5 ",
          "summary": "Gemni 3.5 Pro到底啥时候来啊！！！...",
          "date": "2026-07-01",
          "source": "量子位",
          "type": "industry",
          "tags": [
            "AI",
            "人工智能"
          ]
        },
        {
          "title": "谁能把这个空间高质量地数字化，谁就掌握了下一阶段机器智能的入口。",
          "link": "https://www.qbitai.com/?s=谁能把这个空间高质量",
          "summary": "谁能把这个空间高质量地数字化，谁就掌握了下一阶段机器智能的入口。...",
          "date": "2026-07-01",
          "source": "量子位",
          "type": "industry",
          "tags": [
            "AI",
            "人工智能"
          ]
        },
        {
          "title": "AI进入生物制造，真正缺的不是更聪明的大脑，而是连接数字与物理世界的接口。",
          "link": "https://www.qbitai.com/?s=AI进入生物制造，真",
          "summary": "AI进入生物制造，真正缺的不是更聪明的大脑，而是连接数字与物理世界的接口。...",
          "date": "2026-07-01",
          "source": "量子位",
          "type": "industry",
          "tags": [
            "AI",
            "人工智能"
          ]
        }
      ]
    },
    "economy": {
      "name": "宏观经济",
      "icon": "📈",
      "count": 0,
      "items": []
    },
    "realestate": {
      "name": "房地产",
      "icon": "🏠",
      "count": 0,
      "items": []
    },
    "chip": {
      "name": "芯片半导体",
      "icon": "💻",
      "count": 0,
      "items": []
    }
  },
  "hot_topics": [
    "AI大模型",
    "美联储利率决议",
    "房贷利率",
    "芯片出口管制"
  ]
}