{
  "last_updated": "2026-04-03",
  "count": 5,
  "items": [
    {
      "title": "ActionParty: Multi-Subject Action Binding in Generative Video Games",
      "authors": "Alexander Pondaven, Ziyi Wu, Igor Gilitschenski et al.",
      "abstract": "Recent advances in video diffusion have enabled the development of \"world models\" capable of simulating interactive environments. However, these models are largely restricted to single-agent settings, failing to control multiple agents simultaneously in a scene. In this work, we tackle a fundamental...",
      "venue": "arXiv",
      "date": "2026-04-02",
      "arxiv_id": "2604.02330v1",
      "url": "https://arxiv.org/abs/2604.02330v1",
      "pdf_url": "https://arxiv.org/pdf/2604.02330v1.pdf",
      "categories": [
        "cs.CV",
        "cs.AI",
        "cs.LG"
      ],
      "type": "vision",
      "badge": "arxiv",
      "source": "arXiv"
    },
    {
      "title": "Steerable Visual Representations",
      "authors": "Jona Ruthardt, Manu Gaur, Deva Ramanan et al.",
      "abstract": "Pretrained Vision Transformers (ViTs) such as DINOv2 and MAE provide generic image features that can be applied to a variety of downstream tasks such as retrieval, classification, and segmentation. However, such representations tend to focus on the most salient visual cues in the image, with no way ...",
      "venue": "arXiv",
      "date": "2026-04-02",
      "arxiv_id": "2604.02327v1",
      "url": "https://arxiv.org/abs/2604.02327v1",
      "pdf_url": "https://arxiv.org/pdf/2604.02327v1.pdf",
      "categories": [
        "cs.CV",
        "cs.AI"
      ],
      "type": "vision",
      "badge": "arxiv",
      "source": "arXiv"
    },
    {
      "title": "Grounded Token Initialization for New Vocabulary in LMs for Generative Recommendation",
      "authors": "Daiwei Chen, Zhoutong Fu, Chengming Jiang et al.",
      "abstract": "Language models (LMs) are increasingly extended with new learnable vocabulary tokens for domain-specific tasks, such as Semantic-ID tokens in generative recommendation. The standard practice initializes these new tokens as the mean of existing vocabulary embeddings, then relies on supervised fine-tu...",
      "venue": "arXiv",
      "date": "2026-04-02",
      "arxiv_id": "2604.02324v1",
      "url": "https://arxiv.org/abs/2604.02324v1",
      "pdf_url": "https://arxiv.org/pdf/2604.02324v1.pdf",
      "categories": [
        "cs.CL",
        "cs.AI",
        "cs.LG"
      ],
      "type": "nlp",
      "badge": "arxiv",
      "source": "arXiv"
    },
    {
      "title": "Batched Contextual Reinforcement: A Task-Scaling Law for Efficient Reasoning",
      "authors": "Bangji Yang, Hongbo Ma, Jiajun Fan et al.",
      "abstract": "Large Language Models employing Chain-of-Thought reasoning achieve strong performance but suffer from excessive token consumption that inflates inference costs. Existing efficiency methods such as explicit length penalties, difficulty estimators, or multi-stage curricula either degrade reasoning qua...",
      "venue": "arXiv",
      "date": "2026-04-02",
      "arxiv_id": "2604.02322v1",
      "url": "https://arxiv.org/abs/2604.02322v1",
      "pdf_url": "https://arxiv.org/pdf/2604.02322v1.pdf",
      "categories": [
        "cs.LG",
        "cs.AI",
        "cs.CL"
      ],
      "type": "nlp",
      "badge": "arxiv",
      "source": "arXiv"
    },
    {
      "title": "EventHub: Data Factory for Generalizable Event-Based Stereo Networks without Active Sensors",
      "authors": "Luca Bartolomei, Fabio Tosi, Matteo Poggi et al.",
      "abstract": "We propose EventHub, a novel framework for training deep-event stereo networks without ground truth annotations from costly active sensors, relying instead on standard color images. From these images, we derive either proxy annotations and proxy events through state-of-the-art novel view synthesis t...",
      "venue": "arXiv",
      "date": "2026-04-02",
      "arxiv_id": "2604.02331v1",
      "url": "https://arxiv.org/abs/2604.02331v1",
      "pdf_url": "https://arxiv.org/pdf/2604.02331v1.pdf",
      "categories": [
        "cs.CV"
      ],
      "type": "vision",
      "badge": "arxiv",
      "source": "arXiv"
    }
  ]
}